rlforge/__init__.py
rlforge/policies.py
rlforge/utils.py
rlforge/agents/__init__.py
rlforge/agents/bandit.py
rlforge/agents/base_agent.py
rlforge/agents/policy_gradient/__init__.py
rlforge/agents/policy_gradient/ddpg.py
rlforge/agents/policy_gradient/gaussian_actor_critic.py
rlforge/agents/policy_gradient/ppo_continuous.py
rlforge/agents/policy_gradient/ppo_discrete.py
rlforge/agents/policy_gradient/reinforce.py
rlforge/agents/policy_gradient/sac.py
rlforge/agents/policy_gradient/softmax_actor_critic.py
rlforge/agents/policy_gradient/td3.py
rlforge/agents/semi_gradient/__init__.py
rlforge/agents/semi_gradient/dqn.py
rlforge/agents/semi_gradient/dqn_pytorch.py
rlforge/agents/semi_gradient/linear_sg_agent.py
rlforge/agents/tabular/__init__.py
rlforge/agents/tabular/expected_sarsa.py
rlforge/agents/tabular/planning_agent.py
rlforge/agents/tabular/q_agent.py
rlforge/agents/tabular/sarsa.py
rlforge/environments/__init__.py
rlforge/environments/bandits.py
rlforge/environments/dyna_maze.py
rlforge/environments/mecanum_car.py
rlforge/environments/obstacle_avoidance.py
rlforge/environments/pendulum.py
rlforge/environments/pid.py
rlforge/environments/short_corridor.py
rlforge/environments/shortcut_maze.py
rlforge/environments/trajectory_tracking.py
rlforge/experiments/__init__.py
rlforge/experiments/experiment_runner.py
rlforge/feature_extraction/__init__.py
rlforge/feature_extraction/tile_coder.py
rlforge/feature_extraction/tiles3.py
rlforge/function_approximation/__init__.py
rlforge/function_approximation/linear_regression.py
rlforge/function_approximation/mlp.py
rlforge/optimizers/__init__.py
rlforge/optimizers/adam_optimizer.py
rlforge-1.1.0.dist-info/licenses/LICENSE
rlforge-1.1.0.dist-info/METADATA
rlforge-1.1.0.dist-info/WHEEL
rlforge-1.1.0.dist-info/top_level.txt
rlforge-1.1.0.dist-info/RECORD
