Metadata-Version: 2.4
Name: rlforge
Version: 1.1.0
Summary: Reinforcement Learning for Everyone.
Author-email: Alejandro Toro-Ossaba <alejotoro.o@gmail.com>
License-Expression: MIT
Project-URL: Homepage, https://github.com/alejotoro-o/rlforge
Project-URL: Documentation, https://rlforge.readthedocs.io/
Project-URL: Repository, https://github.com/alejotoro-o/rlforge
Project-URL: Bug Tracker, https://github.com/alejotoro-o/rlforge/issues
Keywords: reinforcement learning,machine learning
Classifier: Programming Language :: Python :: 3
Classifier: Operating System :: OS Independent
Requires-Python: >=3.10
License-File: LICENSE
Requires-Dist: numpy>=2.2.0
Requires-Dist: tqdm>=4.67.1
Requires-Dist: gymnasium>=1.2.2
Requires-Dist: matplotlib>=3.10.7
Provides-Extra: torch
Requires-Dist: torch>=2.9.0; extra == "torch"
Provides-Extra: all
Requires-Dist: torch>=2.9.0; extra == "all"
Dynamic: license-file
